dmc/__init__.py
dmc/data_utils.py
dmc/io.py
dmc/model_utils.py
dmc/models.py
dmc/plotting.py
eht_dmc-0.1.dev0.dist-info/LICENSE
eht_dmc-0.1.dev0.dist-info/METADATA
eht_dmc-0.1.dev0.dist-info/WHEEL
eht_dmc-0.1.dev0.dist-info/top_level.txt
eht_dmc-0.1.dev0.dist-info/RECORD
