Metadata-Version: 2.1
Name: eht-dmc
Version: 0.1.dev0
Summary: Python code to perform radio interferometric imaging and modeling within a Bayesian framework in both total intensity and polarization.
Home-page: https://github.com/dpesce/DMC
Author: Dom Pesce
Author-email: dpesce@cfa.harvard.edu
License: GPLv3
Keywords: radio interferometry VLBI
Platform: UNKNOWN
Requires-Dist: ehtim
Requires-Dist: pymc3
Requires-Dist: future
Requires-Dist: matplotlib
Requires-Dist: numpy
Requires-Dist: scipy
Requires-Dist: corner
Requires-Dist: ehtplot
